{
    "id": "Canofgreenpeas",
    "iscontainer": true,
    "originPrefab": "nutrientbar",
    "fullname": "豌豆罐头",
    "description": "富含维生素和硒的豌豆罐头，在“诺文斯克”地区更能凸显出它的价值\n<color=#88ff88>“当然，在这里也是”</color>\n<color=#00ffff>完全食用后：+35能量+5水分/可食用5次</color>",
    "category": "food",
    "slotRotation": 0,
    "usable": true,
    "usableOnLimb": true,
    "rotSpeed": 0,
    "useAction": {
        "eat": {
            "hungerAmount": 7,
            "weightGain": 0,
            "drinkAmount": 1,
            "sicknessAmount": 0,
            "happiness": 0,
            "conditionConsumption": 0.2,
            "talker": "eatMediocre",
            "sound": "eatFlesh"
        }
    },
    "useLimbAction": null,
    "destroyAtZeroCondition": true,
    "weight": 0.46,
    "value": 0,
    "decayMinutes": 0,
    "recognition": 0
}